flitenv/__init__.py
flitenv/__main__.py
flitenv/_cli.py
flitenv/_constants.py
flitenv/_deps_manager.py
flitenv/_meta.py
flitenv/_venv.py
flitenv/commands/__init__.py
flitenv/commands/_base.py
flitenv/commands/_deps.py
flitenv/commands/_install.py
flitenv/commands/_lock.py
flitenv/commands/_run.py
flitenv/commands/_version.py
flitenv-0.4.0.dist-info/entry_points.txt
flitenv-0.4.0.dist-info/LICENSE
flitenv-0.4.0.dist-info/WHEEL
flitenv-0.4.0.dist-info/METADATA
flitenv-0.4.0.dist-info/RECORD
